automs/__init__.py
automs/automs.py
automs/classification_complexity_prediction.py
automs/cluster_indices_generation.py
automs/config.py
automs/eda.py
automs/exceptions.py
automs/external_indices.py
automs/f1_scores_estimation.py
automs/internal_indices.py
automs/main.py
automs/sampling.py
automs/true_f1_scores_computation.py
automs/utils.py
automs/models/decision_tree_f1_estimator.onnx
automs/models/features.pkl
automs/models/hardness_classifier.onnx
automs/models/k_nearest_neighbor_f1_estimator.onnx
automs/models/logistic_regression_f1_estimator.onnx
automs/models/random_forest_f1_estimator.onnx
automs/models/support_vector_machine_f1_estimator.onnx
automs/models/xgboost_f1_estimator.onnx
automs-0.1.0.data/scripts/automs-config
automs-0.1.0.dist-info/LICENSE.txt
automs-0.1.0.dist-info/METADATA
automs-0.1.0.dist-info/WHEEL
automs-0.1.0.dist-info/entry_points.txt
automs-0.1.0.dist-info/top_level.txt
automs-0.1.0.dist-info/RECORD
