Metadata-Version: 2.1
Name: automs
Version: 0.1.0
Summary: Automatic Model Selection Using Cluster Indices
Home-page: https://automs.readthedocs.io
Author: Sudarsun Santhiappan, Nitin Shravan, Mukesh Reghu
Author-email: mail@sudarsun.in, ntnshrav@gmail.com, reghu.mukesh@gmail.com
Maintainer: Mukesh Reghu
Maintainer-email: reghu.mukesh@gmail.com
License: 3-clause-BSD
Project-URL: Documentation, https://automs.readthedocs.io
Project-URL: Source, https://github.com/RBC-DSAI-IITM/AutoMS
Project-URL: Tracker, https://github.com/RBC-DSAI-IITM/AutoMS/issues
Keywords: automatic classification model selection cluster indices
Platform: UNKNOWN
Classifier: Development Status :: 5 - Production/Stable
Classifier: Intended Audience :: Science/Research
Classifier: Topic :: Scientific/Engineering :: Artificial Intelligence
Classifier: License :: OSI Approved :: BSD License
Classifier: Programming Language :: Python :: 3.6
Classifier: Programming Language :: Python :: 3 :: Only
Classifier: Operating System :: POSIX :: Linux
Requires-Python: ~=3.6
Requires-Dist: npyscreen
Requires-Dist: scipy
Requires-Dist: matplotlib
Requires-Dist: hdbscan
Requires-Dist: pandas
Requires-Dist: seaborn
Requires-Dist: scikit-learn
Requires-Dist: tqdm
Requires-Dist: onnxruntime
Requires-Dist: numpy
Requires-Dist: xgboost
Requires-Dist: cython
Requires-Dist: openpyxl
